jupyterlab_execute_time/__init__.py
jupyterlab_execute_time/_version.py
jupyterlab_execute_time/labextension/build_log.json
jupyterlab_execute_time/labextension/package.json
jupyterlab_execute_time/labextension/schemas/jupyterlab-execute-time/package.json.orig
jupyterlab_execute_time/labextension/schemas/jupyterlab-execute-time/settings.json
jupyterlab_execute_time/labextension/static/lib_index_js.110050644687415cca75.js
jupyterlab_execute_time/labextension/static/lib_index_js.110050644687415cca75.js.map
jupyterlab_execute_time/labextension/static/remoteEntry.c1fc9ff3552b89e3dea6.js
jupyterlab_execute_time/labextension/static/remoteEntry.c1fc9ff3552b89e3dea6.js.map
jupyterlab_execute_time/labextension/static/style.js
jupyterlab_execute_time/labextension/static/style_index_js.e3248b207ee2564c1324.js
jupyterlab_execute_time/labextension/static/style_index_js.e3248b207ee2564c1324.js.map
jupyterlab_execute_time/labextension/static/vendors-node_modules_date-fns_esm_index_js.bb5155b17a678353747a.js
jupyterlab_execute_time/labextension/static/vendors-node_modules_date-fns_esm_index_js.bb5155b17a678353747a.js.map
jupyterlab_execute_time-3.2.0.data/data/share/jupyter/labextensions/jupyterlab-execute-time/build_log.json
jupyterlab_execute_time-3.2.0.data/data/share/jupyter/labextensions/jupyterlab-execute-time/install.json
jupyterlab_execute_time-3.2.0.data/data/share/jupyter/labextensions/jupyterlab-execute-time/package.json
jupyterlab_execute_time-3.2.0.data/data/share/jupyter/labextensions/jupyterlab-execute-time/schemas/jupyterlab-execute-time/package.json.orig
jupyterlab_execute_time-3.2.0.data/data/share/jupyter/labextensions/jupyterlab-execute-time/schemas/jupyterlab-execute-time/settings.json
jupyterlab_execute_time-3.2.0.data/data/share/jupyter/labextensions/jupyterlab-execute-time/static/lib_index_js.110050644687415cca75.js
jupyterlab_execute_time-3.2.0.data/data/share/jupyter/labextensions/jupyterlab-execute-time/static/lib_index_js.110050644687415cca75.js.map
jupyterlab_execute_time-3.2.0.dist-info/LICENSE.txt
jupyterlab_execute_time-3.2.0.dist-info/METADATA
jupyterlab_execute_time-3.2.0.dist-info/WHEEL
jupyterlab_execute_time-3.2.0.dist-info/top_level.txt
jupyterlab_execute_time-3.2.0.dist-info/RECORD
