Metadata-Version: 2.1
Name: jupyterlab_execute_time
Version: 3.2.0
Summary: Display cell timings in Jupyter Lab
Home-page: https://github.com/deshaw/jupyterlab-execute-time
Author: Marc Udoff
License: BSD-3-Clause
Keywords: Jupyter,JupyterLab,JupyterLab4
Platform: Linux
Platform: Mac OS X
Platform: Windows
Classifier: License :: OSI Approved :: BSD License
Classifier: Programming Language :: Python
Classifier: Programming Language :: Python :: 3
Classifier: Programming Language :: Python :: 3.7
Classifier: Programming Language :: Python :: 3.8
Classifier: Programming Language :: Python :: 3.9
Classifier: Programming Language :: Python :: 3.10
Classifier: Programming Language :: Python :: 3.11
Classifier: Framework :: Jupyter
Classifier: Framework :: Jupyter :: JupyterLab
Classifier: Framework :: Jupyter :: JupyterLab :: 4
Classifier: Framework :: Jupyter :: JupyterLab :: Extensions
Classifier: Framework :: Jupyter :: JupyterLab :: Extensions :: Prebuilt
Requires-Python: >=3.7
License-File: LICENSE.txt
Requires-Dist: jupyterlab<5,>=4
